pypvroof/__init__.py
pypvroof/main.py
pypvroof/methods.py
pypvroof/setup.py
pypvroof/utils.py
pypvroof/data/lut_france.json
pypvroof-0.1.1.dist-info/licenses/LICENSE
pypvroof-0.1.1.dist-info/METADATA
pypvroof-0.1.1.dist-info/WHEEL
pypvroof-0.1.1.dist-info/top_level.txt
pypvroof-0.1.1.dist-info/RECORD
