Metadata-Version: 2.4
Name: pypvroof
Version: 0.1.1
Summary: A Python package for PV roof mapping and analysis
Home-page: https://github.com/gabrielkasmi/pypvroof
Author: Gabriel Kasmi
Author-email: gabriel.kasmi@minesparis.psl.eu
Classifier: Programming Language :: Python :: 3
Classifier: License :: OSI Approved :: MIT License
Classifier: Operating System :: OS Independent
Requires-Python: >=3.8
License-File: LICENSE
Requires-Dist: numpy>=1.21.0
Requires-Dist: pandas>=1.3.0
Requires-Dist: scikit-learn>=1.0.0
Requires-Dist: matplotlib>=3.4.0
Requires-Dist: geojson>=2.5.0
Requires-Dist: tqdm>=4.62.0
Requires-Dist: shapely>=1.8.0
Requires-Dist: rasterio>=1.2.0
Provides-Extra: gdal
Requires-Dist: GDAL>=3.6.2; extra == "gdal"
Provides-Extra: dev
Requires-Dist: pytest>=6.0; extra == "dev"
Requires-Dist: black>=21.0; extra == "dev"
Requires-Dist: flake8>=3.9; extra == "dev"
Dynamic: author
Dynamic: author-email
Dynamic: classifier
Dynamic: description
Dynamic: description-content-type
Dynamic: home-page
Dynamic: license-file
Dynamic: provides-extra
Dynamic: requires-dist
Dynamic: requires-python
Dynamic: summary
